orra/__init__.py
orra/client.py
orra/constants.py
orra/exceptions.py
orra/logger.py
orra/persistence.py
orra/types.py
orra/wrappers.py
orra_sdk-0.2.2.dist-info/METADATA
orra_sdk-0.2.2.dist-info/WHEEL
orra_sdk-0.2.2.dist-info/RECORD
