Metadata-Version: 2.1
Name: orra-sdk
Version: 0.2.2
Summary: Python SDK for Orra - Build reliable multi-agent applications that handle complex real-world interactions.
License: MPL-2.0
Author: Orra Team
Requires-Python: >=3.11,<4.0
Classifier: License :: OSI Approved
Classifier: Programming Language :: Python :: 3
Classifier: Programming Language :: Python :: 3.11
Classifier: Programming Language :: Python :: 3.12
Classifier: Programming Language :: Python :: 3.13
Requires-Dist: httpx (>=0.26.0,<0.27.0)
Requires-Dist: pydantic (>=2.0,<3.0)
Requires-Dist: structlog (>=24.1.0)
Requires-Dist: websockets (>=12.0,<13.0)
